dkconverter/__init__.py
dkconverter/conv.py
dkconverters-1.0.0.dist-info/LICENSE
dkconverters-1.0.0.dist-info/METADATA
dkconverters-1.0.0.dist-info/WHEEL
dkconverters-1.0.0.dist-info/top_level.txt
dkconverters-1.0.0.dist-info/RECORD
