Metadata-Version: 2.1
Name: dkconverters
Version: 1.0.0
Summary: A package to convert between different numeral systems
Home-page: https://github.com/Dev-king-coder/dkpackages
Author: Dev Keshwani
Author-email: dev.keshwani345@gmail.com
Project-URL: Bug Tracker, https://github.com/Dev-king-coder/dkpackages/issues
Classifier: Programming Language :: Python :: 3
Classifier: License :: OSI Approved :: MIT License
Classifier: Operating System :: OS Independent
Requires-Python: >=3.6
License-File: LICENSE
